topsis_102203435/__init__.py
topsis_102203435/cli.py
topsis_102203435/topsis.py
102203435_topsis-0.6.dist-info/METADATA
102203435_topsis-0.6.dist-info/WHEEL
102203435_topsis-0.6.dist-info/entry_points.txt
102203435_topsis-0.6.dist-info/top_level.txt
102203435_topsis-0.6.dist-info/RECORD
