Metadata-Version: 2.1
Name: 102203435-topsis
Version: 0.6
Summary: TOPSIS implementation for best decision-making  
Author: Akshit
Author-email: kharbakshit010@gmail.com
Classifier: Programming Language :: Python :: 3
Classifier: License :: OSI Approved :: MIT License
Classifier: Operating System :: OS Independent
